[{"quantileName":"VMIScheduled","uuid":"182596f6-69ad-4066-bbe9-0dd4c11048c5","P99":756211,"P95":756211,"P50":696449,"max":760370,"avg":715748,"timestamp":"2024-09-06T08:49:06.218785272Z","metricName":"podLatencyQuantilesMeasurement","metadata":{}},{"quantileName":"PodCreated","uuid":"182596f6-69ad-4066-bbe9-0dd4c11048c5","P99":690416,"P95":690416,"P50":688514,"max":691227,"avg":688266,"timestamp":"2024-09-06T08:49:06.218790304Z","metricName":"podLatencyQuantilesMeasurement","metadata":{}},{"quantileName":"PodScheduled","uuid":"182596f6-69ad-4066-bbe9-0dd4c11048c5","P99":690459,"P95":690459,"P50":688562,"max":691243,"avg":688303,"timestamp":"2024-09-06T08:49:06.218791358Z","metricName":"podLatencyQuantilesMeasurement","metadata":{}},{"quantileName":"PodContainersReady","uuid":"182596f6-69ad-4066-bbe9-0dd4c11048c5","P99":756182,"P95":756182,"P50":696269,"max":760342,"avg":715646,"timestamp":"2024-09-06T08:49:06.218792197Z","metricName":"podLatencyQuantilesMeasurement","metadata":{}},{"quantileName":"PodReady","uuid":"182596f6-69ad-4066-bbe9-0dd4c11048c5","P99":756182,"P95":756182,"P50":696269,"max":760342,"avg":715645,"timestamp":"2024-09-06T08:49:06.218793407Z","metricName":"podLatencyQuantilesMeasurement","metadata":{}},{"quantileName":"VMReady","uuid":"182596f6-69ad-4066-bbe9-0dd4c11048c5","P99":760993,"P95":760993,"P50":700412,"max":763961,"avg":719941,"timestamp":"2024-09-06T08:49:06.218794202Z","metricName":"podLatencyQuantilesMeasurement","metadata":{}},{"quantileName":"VMICreated","uuid":"182596f6-69ad-4066-bbe9-0dd4c11048c5","P99":690365,"P95":690365,"P50":688463,"max":691180,"avg":688225,"timestamp":"2024-09-06T08:49:06.218794861Z","metricName":"podLatencyQuantilesMeasurement","metadata":{}},{"quantileName":"VMIPending","uuid":"182596f6-69ad-4066-bbe9-0dd4c11048c5","P99":690395,"P95":690395,"P50":688497,"max":691206,"avg":688254,"timestamp":"2024-09-06T08:49:06.218795574Z","metricName":"podLatencyQuantilesMeasurement","metadata":{}},{"quantileName":"VMIScheduling","uuid":"182596f6-69ad-4066-bbe9-0dd4c11048c5","P99":690652,"P95":690652,"P50":688757,"max":691392,"avg":688477,"timestamp":"2024-09-06T08:49:06.218796223Z","metricName":"podLatencyQuantilesMeasurement","metadata":{}},{"quantileName":"VMIReady","uuid":"182596f6-69ad-4066-bbe9-0dd4c11048c5","P99":760978,"P95":760978,"P50":700519,"max":763929,"avg":719948,"timestamp":"2024-09-06T08:49:06.218797849Z","metricName":"podLatencyQuantilesMeasurement","metadata":{}},{"quantileName":"PodInitialized","uuid":"182596f6-69ad-4066-bbe9-0dd4c11048c5","P99":690533,"P95":690533,"P50":688990,"max":691287,"avg":688464,"timestamp":"2024-09-06T08:49:06.218798416Z","metricName":"podLatencyQuantilesMeasurement","metadata":{}}]
